ai_core/__init__.py
ai_core/chat.py
ai_core/message.py
ai_core/model.py
ai_core/template.py
ai_core/util.py
app/__init__.py
app/chat_core.py
app/chat_manager.py
app/config_manager.py
app/constants.py
app/main.py
app/model_manager.py
app/util.py
terminal_ai_chat-0.1.6.dist-info/METADATA
terminal_ai_chat-0.1.6.dist-info/WHEEL
terminal_ai_chat-0.1.6.dist-info/entry_points.txt
terminal_ai_chat-0.1.6.dist-info/top_level.txt
terminal_ai_chat-0.1.6.dist-info/RECORD
