Metadata-Version: 2.4
Name: terminal-ai-chat
Version: 0.1.6
Summary: A simple CLI tool to talk to an LLM in the terminal.
Author-email: Anas Ahmed <anas.ia.ahmed@gmail.com>
License-Expression: MIT
Project-URL: repository, https://github.com/robot1273/terminal_ai_chat
Requires-Dist: typer
Requires-Dist: PyYAML
Requires-Dist: rich
Requires-Dist: requests
Requires-Dist: platformdirs
Requires-Dist: python-dotenv
